python_print_tools/__init__.py
python_print_tools/printer.py
python_print_tools/tests/__init__.py
python_print_tools/tests/test_printer.py
Python_Print_Tools-0.2.2.dist-info/LICENSE
Python_Print_Tools-0.2.2.dist-info/METADATA
Python_Print_Tools-0.2.2.dist-info/WHEEL
Python_Print_Tools-0.2.2.dist-info/top_level.txt
Python_Print_Tools-0.2.2.dist-info/RECORD
