Metadata-Version: 2.1
Name: Python-Print-Tools
Version: 0.2.2
Summary: Basic utility for printing info to console.
Home-page: https://github.com/Drakovek/Python-Print-Tools
Author: Drakovek
Author-email: DrakovekMail@gmail.com
Classifier: Programming Language :: Python :: 3
Classifier: License :: OSI Approved :: GNU General Public License v3 (GPLv3)
Classifier: Operating System :: OS Independent
Requires-Python: >=3.0
License-File: LICENSE
